flashfreeze/__init__.py
flashfreeze/ffdirectory.py
flashfreeze/gitclient.py
flashfreeze-0.1.data/scripts/flashfreeze
flashfreeze-0.1.dist-info/LICENSE
flashfreeze-0.1.dist-info/METADATA
flashfreeze-0.1.dist-info/WHEEL
flashfreeze-0.1.dist-info/top_level.txt
flashfreeze-0.1.dist-info/RECORD
