Metadata-Version: 2.1
Name: flashfreeze
Version: 0.1
Summary: A modern rewrite of FlashBack
Home-page: https://gitlab.com/blfordham/flashfreeze
Author: Bryan Fordham
Author-email: bryan@nativesavannah.com
License: UNKNOWN
Platform: UNKNOWN
Classifier: Programming Language :: Python :: 3
Classifier: License :: OSI Approved :: MIT License
Classifier: Operating System :: OS Independent
